[
  {
    "index": 0,
    "name": "上田　朋和",
    "slug": "0"
  },
  {
    "index": 1,
    "name": "稲垣　清也",
    "slug": "1"
  },
  {
    "index": 2,
    "name": "一色　眞一",
    "slug": "2"
  },
  {
    "index": 3,
    "name": "上野　清隆",
    "slug": "3"
  },
  {
    "index": 4,
    "name": "福永　哲也",
    "slug": "4"
  },
  {
    "index": 5,
    "name": "東野　真樹",
    "slug": "5"
  },
  {
    "index": 6,
    "name": "若林　高",
    "slug": "6"
  },
  {
    "index": 7,
    "name": "髙橋　菜見子",
    "slug": "7"
  },
  {
    "index": 8,
    "name": "林　茂信",
    "slug": "8"
  },
  {
    "index": 9,
    "name": "山口　忠志",
    "slug": "9"
  },
  {
    "index": 10,
    "name": "林　直史",
    "slug": "10"
  },
  {
    "index": 11,
    "name": "川下　勉",
    "slug": "11"
  },
  {
    "index": 12,
    "name": "前田　正",
    "slug": "12"
  },
  {
    "index": 13,
    "name": "辰川　志郎",
    "slug": "13"
  },
  {
    "index": 14,
    "name": "中谷　喜英",
    "slug": "14"
  },
  {
    "index": 15,
    "name": "植木　陽祐",
    "slug": "15"
  },
  {
    "index": 16,
    "name": "荒谷　啓一",
    "slug": "16"
  },
  {
    "index": 17,
    "name": "林　俊昭",
    "slug": "17"
  },
  {
    "index": 18,
    "name": "南出　貞子",
    "slug": "18"
  },
  {
    "index": 19,
    "name": "中川　敬雄",
    "slug": "19"
  },
  {
    "index": 20,
    "name": "辻　裕行",
    "slug": "20"
  }
]